MANIFEST.in
README.rst
setup.py
relate.egg-info/PKG-INFO
relate.egg-info/SOURCES.txt
relate.egg-info/dependency_links.txt
relate.egg-info/top_level.txt
src/__init__.py
src/relate.py