Metadata-Version: 1.1
Name: relate
Version: 0.1
Summary: Discrete mathematical relation
Home-page: https://github.com/scott-howard-james/relate.git
Author: Scott Howard James
Author-email: scott.analysis.james@gmail.com
License: MIT
Platform: UNKNOWN
Classifier: Development Status :: 4 - Beta
Classifier: Intended Audience :: Developers
Classifier: License :: Freeware
Classifier: Operating System :: OS Independent
Classifier: Programming Language :: Python :: 3
Classifier: Topic :: Software Development :: Libraries :: Python Modules
